cluster_tools/__init__.py
cluster_tools/executor_protocol.py
cluster_tools/remote.py
cluster_tools/version.py
cluster_tools/_utils/call.py
cluster_tools/_utils/file_wait_thread.py
cluster_tools/_utils/multiprocessing_logging_handler.py
cluster_tools/_utils/pickling.py
cluster_tools/_utils/reflection.py
cluster_tools/_utils/string_.py
cluster_tools/_utils/tailf.py
cluster_tools/_utils/warning.py
cluster_tools/executors/dask.py
cluster_tools/executors/multiprocessing_.py
cluster_tools/executors/multiprocessing_pickle.py
cluster_tools/executors/sequential.py
cluster_tools/executors/sequential_pickle.py
cluster_tools/schedulers/__init__.py
cluster_tools/schedulers/cluster_executor.py
cluster_tools/schedulers/kube.py
cluster_tools/schedulers/pbs.py
cluster_tools/schedulers/slurm.py
cluster_tools-3.1.3.dist-info/licenses/LICENSE
cluster_tools-3.1.3.dist-info/METADATA
cluster_tools-3.1.3.dist-info/WHEEL
cluster_tools-3.1.3.dist-info/top_level.txt
cluster_tools-3.1.3.dist-info/RECORD
