Metadata-Version: 2.4
Name: cluster_tools
Version: 3.1.3
Summary: Utility library for easily distributing code execution on clusters
Author-email: scalable minds <hello@scalableminds.com>
License-Expression: MIT
Project-URL: Repository, https://github.com/scalableminds/webknossos-libs
Project-URL: Changelog, https://github.com/scalableminds/webknossos-libs/blob/master/cluster_tools/Changelog.md
Requires-Python: >=3.10
License-File: LICENSE
Requires-Dist: typing-extensions~=4.12.0
Provides-Extra: dask
Requires-Dist: distributed~=2023.9.1; extra == "dask"
Provides-Extra: kubernetes
Requires-Dist: kubernetes~=27.2.0; extra == "kubernetes"
Provides-Extra: all
Requires-Dist: cluster_tools[kubernetes]; extra == "all"
Requires-Dist: cluster_tools[dask]; extra == "all"
Dynamic: license-file
